odoo/addons/product_search_category_attribute_stock/README.rst
odoo/addons/product_search_category_attribute_stock/__init__.py
odoo/addons/product_search_category_attribute_stock/__manifest__.py
odoo/addons/product_search_category_attribute_stock/models/__init__.py
odoo/addons/product_search_category_attribute_stock/models/product_search_category_attribute.py
odoo/addons/product_search_category_attribute_stock/readme/CONTRIBUTORS.md
odoo/addons/product_search_category_attribute_stock/readme/DESCRIPTION.md
odoo/addons/product_search_category_attribute_stock/readme/USAGE.md
odoo/addons/product_search_category_attribute_stock/static/description/icon.png
odoo/addons/product_search_category_attribute_stock/static/description/index.html
odoo/addons/product_search_category_attribute_stock/views/product_search_category_attribute_views.xml
odoo_addon_product_search_category_attribute_stock-16.0.1.0.0.1.dist-info/METADATA
odoo_addon_product_search_category_attribute_stock-16.0.1.0.0.1.dist-info/WHEEL
odoo_addon_product_search_category_attribute_stock-16.0.1.0.0.1.dist-info/top_level.txt
odoo_addon_product_search_category_attribute_stock-16.0.1.0.0.1.dist-info/RECORD
